Metadata-Version: 1.0
Name: gbXMLParser
Version: 0.64
Summary: Parser for gbXML file
Home-page: https://git.autodesk.com/t-songr/gbXML_parser
Author: Runsheng Song
Author-email: runsheng@umail.ucsb.edu
License: MIT
Platform: UNKNOWN
